{"fixedCells":[{"r":0,"c":7,"value":2},{"r":2,"c":0,"value":9},{"r":2,"c":4,"value":8},{"r":2,"c":8,"value":1},{"r":3,"c":1,"value":6},{"r":4,"c":4,"value":2},{"r":5,"c":7,"value":4},{"r":6,"c":0,"value":1},{"r":6,"c":4,"value":6},{"r":6,"c":5,"value":7},{"r":6,"c":8,"value":3},{"r":8,"c":1,"value":4}],"rules":[{"type":"Standard","fields":{},"rules":[]},{"type":"Clone","fields":{},"rules":[{"id":"1747559447455-vqsp","fields":{"region":{"__type__":"Region","type":"cells","items":[{"__type__":"CellIdx","r":0,"c":0},{"__type__":"CellIdx","r":0,"c":1},{"__type__":"CellIdx","r":0,"c":2},{"__type__":"CellIdx","r":0,"c":3},{"__type__":"CellIdx","r":1,"c":0},{"__type__":"CellIdx","r":1,"c":3},{"__type__":"CellIdx","r":2,"c":0},{"__type__":"CellIdx","r":2,"c":3},{"__type__":"CellIdx","r":3,"c":0},{"__type__":"CellIdx","r":3,"c":1},{"__type__":"CellIdx","r":3,"c":2},{"__type__":"CellIdx","r":3,"c":3}]},"color":"rgba(171, 25, 71, 0.3)"}},{"id":"1747559460180-b39x","fields":{"region":{"__type__":"Region","type":"cells","items":[{"__type__":"CellIdx","r":5,"c":5},{"__type__":"CellIdx","r":5,"c":6},{"__type__":"CellIdx","r":5,"c":7},{"__type__":"CellIdx","r":5,"c":8},{"__type__":"CellIdx","r":6,"c":5},{"__type__":"CellIdx","r":6,"c":8},{"__type__":"CellIdx","r":7,"c":5},{"__type__":"CellIdx","r":7,"c":8},{"__type__":"CellIdx","r":8,"c":5},{"__type__":"CellIdx","r":8,"c":6},{"__type__":"CellIdx","r":8,"c":7},{"__type__":"CellIdx","r":8,"c":8}]},"color":"rgba(233, 92, 248, 0.3)"}}]}]}